streamlit_condition_tree/__init__.py
streamlit_condition_tree/example.py
streamlit_condition_tree/frontend/build/asset-manifest.json
streamlit_condition_tree/frontend/build/bootstrap.min.css
streamlit_condition_tree/frontend/build/index.html
streamlit_condition_tree/frontend/build/static/css/main.1646680d.css
streamlit_condition_tree/frontend/build/static/css/main.1646680d.css.map
streamlit_condition_tree/frontend/build/static/js/main.020c1481.js
streamlit_condition_tree/frontend/build/static/js/main.020c1481.js.LICENSE.txt
streamlit_condition_tree/frontend/build/static/js/main.020c1481.js.map
streamlit_condition_tree/frontend/build/static/js/main.4ac53d0f.js
streamlit_condition_tree/frontend/build/static/js/main.4ac53d0f.js.LICENSE.txt
streamlit_condition_tree/frontend/build/static/js/main.4ac53d0f.js.map
streamlit_condition_tree/frontend/build/static/js/main.54717468.js
streamlit_condition_tree/frontend/build/static/js/main.54717468.js.LICENSE.txt
streamlit_condition_tree/frontend/build/static/js/main.54717468.js.map
streamlit_condition_tree/frontend/build/static/media/source-sans-pro-cyrillic-400-normal.153bee8d873292f9df39.woff2
streamlit_condition_tree/frontend/build/static/media/source-sans-pro-cyrillic-400-normal.a00a7030792ec450d68c.woff
streamlit_condition_tree/frontend/build/static/media/source-sans-pro-cyrillic-ext-400-normal.3fe9e8e4c00e9124b9c7.woff
streamlit_condition_tree/frontend/build/static/media/source-sans-pro-cyrillic-ext-400-normal.de95c5209ef26bf69ccf.woff2
streamlit_condition_tree/frontend/build/static/media/source-sans-pro-greek-400-normal.3c06b5e22c42ade5562f.woff
streamlit_condition_tree/frontend/build/static/media/source-sans-pro-greek-400-normal.9c7d72dcc7a044db07b1.woff2
streamlit_condition_tree/frontend/build/static/media/source-sans-pro-greek-ext-400-normal.1b1cb10170f2616853f0.woff2
streamlit_condition_tree/frontend/build/static/media/source-sans-pro-greek-ext-400-normal.7a64c855edb8d403283b.woff
streamlit_condition_tree-0.3.0.dist-info/LICENSE
streamlit_condition_tree-0.3.0.dist-info/METADATA
streamlit_condition_tree-0.3.0.dist-info/WHEEL
streamlit_condition_tree-0.3.0.dist-info/top_level.txt
streamlit_condition_tree-0.3.0.dist-info/RECORD
