Metadata-Version: 2.1
Name: streamlit-condition-tree
Version: 0.3.0
Summary: Condition Tree Builder for Streamlit
Home-page: https://github.com/cedricvlt/streamlit-condition-tree
Author: Cédric Villette
Author-email: cedric_villette@hotmail.fr
Requires-Python: >=3.7
License-File: LICENSE
Requires-Dist: streamlit (>=0.63)
Provides-Extra: devel
Requires-Dist: wheel ; extra == 'devel'
Requires-Dist: pytest (==7.4.0) ; extra == 'devel'
Requires-Dist: playwright (==1.36.0) ; extra == 'devel'
Requires-Dist: requests (==2.31.0) ; extra == 'devel'
Requires-Dist: pytest-playwright-snapshot (==1.0) ; extra == 'devel'
Requires-Dist: pytest-rerunfailures (==12.0) ; extra == 'devel'
